README.md
setup.cfg
setup.py
lp_push_notifications/__init__.py
lp_push_notifications/admin.py
lp_push_notifications/apps.py
lp_push_notifications/base.py
lp_push_notifications/client.py
lp_push_notifications/models.py
lp_push_notifications/serializers.py
lp_push_notifications/test_device_api.py
lp_push_notifications/test_notificationreceipt_api.py
lp_push_notifications/tests.py
lp_push_notifications/urls.py
lp_push_notifications/views.py
lp_push_notifications.egg-info/PKG-INFO
lp_push_notifications.egg-info/SOURCES.txt
lp_push_notifications.egg-info/dependency_links.txt
lp_push_notifications.egg-info/top_level.txt
lp_push_notifications/fixtures/notificationreceipts.json
lp_push_notifications/fixtures/users.json
lp_push_notifications/migrations/0001_initial.py
lp_push_notifications/migrations/0002_notificationreceipt_payload.py
lp_push_notifications/migrations/__init__.py