Metadata-Version: 1.1
Name: lp-push-notifications
Version: 0.1.7
Summary: REST Framework for Push Notifications
Home-page: https://github.com/Launchpeer/django-rest-push-notifications
Author: Jim Simon
Author-email: hello@launchpeer.com
License: UNKNOWN
Download-URL: https://github.com/Launchpeer/django-rest-push-notifications/archive/master.tar.gz
Platform: UNKNOWN
